{"market":{"mkt":"pt-BR"},"images":[{"startdate":"20251204","fullstartdate":"202512040300","enddate":"20251205","url":"/th?id=OHR.CheetahMound_PT-BR1635774221_1920x1080.jpg&rf=LaDigue_1920x1080.jpg&pid=hp","urlbase":"/th?id=OHR.CheetahMound_PT-BR1635774221","copyright":"Guepardo na Reserva Nacional Maasai Mara, Narok, Quênia (© Andy Rouse/naturepl.com)","copyrightlink":"/search?q=Guepardo+na+%c3%81frica&form=hpcapt&mkt=pt-br","title":"Corrida pela sobrevivência","quiz":"/search?q=Bing+homepage+quiz&filters=WQOskey:%22HPQuiz_20251204_CheetahMound%22&FORM=HPQUIZ","wp":true,"hsh":"bcc40edc2c1f508d139d5898d5ec3e07","drk":1,"top":1,"bot":1,"hs":[],"og":{"img":"https://www.bing.com/th?id=OHR.CheetahMound_PT-BR1635774221_tmb.jpg","title":"Corrida pela sobrevivência","desc":"Dia Internacional do Guepardo","hash":"xVsYN6bJfz9XINAWhh1AjxIA3xfb4W3eyJYT648mtiA="}},{"startdate":"20251203","fullstartdate":"202512030300","enddate":"20251204","url":"/th?id=OHR.BosqueCranes_PT-BR1405246976_1920x1080.jpg&rf=LaDigue_1920x1080.jpg&pid=hp","urlbase":"/th?id=OHR.BosqueCranes_PT-BR1405246976","copyright":"Grous-canadenses ao nascer do sol no Bosque del Apache National Wildlife Refuge, Novo México, EUA (© Jack Dykinga/Minden Pictures)","copyrightlink":"/search?q=Grou-canadiano+ave&form=hpcapt&mkt=pt-br","title":"O amanhecer dos Grous","quiz":"/search?q=Bing+homepage+quiz&filters=WQOskey:%22HPQuiz_20251203_BosqueCranes%22&FORM=HPQUIZ","wp":true,"hsh":"a7e22c53dd35cb9ccace73633e9b63a3","drk":1,"top":1,"bot":1,"hs":[],"og":{"img":"https://www.bing.com/th?id=OHR.BosqueCranes_PT-BR1405246976_tmb.jpg","title":"O amanhecer dos Grous","desc":"Grous-canadenses no Bosque del Apache National Wildlife Refuge, Novo México, EUA","hash":"mnO4lJhZ7nYS/NH2AeZosc9mEfedvhjN9rU03H7ulvw="}},{"startdate":"20251202","fullstartdate":"202512020300","enddate":"20251203","url":"/th?id=OHR.SambaDay_PT-BR0875547071_1920x1080.jpg&rf=LaDigue_1920x1080.jpg&pid=hp","urlbase":"/th?id=OHR.SambaDay_PT-BR0875547071","copyright":"Carnaval no Rio de Janeiro, RJ (© Richard I'Anson/Getty Images)","copyrightlink":"/search?q=Dia+do+samba+no+Brasil&form=hpcapt&mkt=pt-br","title":"Ritmo e identidade brasileira","quiz":"/search?q=Bing+homepage+quiz&filters=WQOskey:%22HPQuiz_20251202_SambaDay%22&FORM=HPQUIZ","wp":true,"hsh":"36ba261505d6bb79879026ce65a0e298","drk":1,"top":1,"bot":1,"hs":[],"og":{"img":"https://www.bing.com/th?id=OHR.SambaDay_PT-BR0875547071_tmb.jpg","title":"Ritmo e identidade brasileira","desc":"Dia Nacional do Samba","hash":"FNVcNkpoEtMFsd5NXdxvIWNNUeVmSGTUg19ihY6K9S0="}},{"startdate":"20251201","fullstartdate":"202512010300","enddate":"20251202","url":"/th?id=OHR.AntarcticArch_PT-BR0722727107_1920x1080.jpg&rf=LaDigue_1920x1080.jpg&pid=hp","urlbase":"/th?id=OHR.AntarcticArch_PT-BR0722727107","copyright":"Arco natural esculpido em um iceberg, Antártida (© Gabrielle/Adobe Stock)","copyrightlink":"/search?q=Dia+da+Ant%c3%a1rtica&form=hpcapt&mkt=pt-br","title":"Beleza, ciência e responsabilidade","quiz":"/search?q=Bing+homepage+quiz&filters=WQOskey:%22HPQuiz_20251201_AntarcticArch%22&FORM=HPQUIZ","wp":true,"hsh":"2ce33c9639cc63b6091b3033b2a90608","drk":1,"top":1,"bot":1,"hs":[],"og":{"img":"https://www.bing.com/th?id=OHR.AntarcticArch_PT-BR0722727107_tmb.jpg","title":"Beleza, ciência e responsabilidade","desc":"Dia da Antártica","hash":"De0HfRz67D9hNdN8Y1945jljlkWf9OZMrVJxKHcC0r8="}},{"startdate":"20251130","fullstartdate":"202511300300","enddate":"20251201","url":"/th?id=OHR.LeipzigMarket_PT-BR0321672309_1920x1080.jpg&rf=LaDigue_1920x1080.jpg&pid=hp","urlbase":"/th?id=OHR.LeipzigMarket_PT-BR0321672309","copyright":"Mercado de Natal em Leipzig, Alemanha (© Krzysztof Baranowski/Getty Images)","copyrightlink":"/search?q=Leipzig%2c+Alemanha&form=hpcapt&mkt=pt-br","title":"Brilho por todo o caminho","quiz":"/search?q=Bing+homepage+quiz&filters=WQOskey:%22HPQuiz_20251130_LeipzigMarket%22&FORM=HPQUIZ","wp":true,"hsh":"cf09b32f1f55e21aa5af9898570820c3","drk":1,"top":1,"bot":1,"hs":[],"og":{"img":"https://www.bing.com/th?id=OHR.LeipzigMarket_PT-BR0321672309_tmb.jpg","title":"Brilho por todo o caminho","desc":"Mercado de Natal em Leipzig, Alemanha","hash":"yXvsI/3ZVdhA7BPRHafPeVHsi2Vv7eDqU80+UE9MTIc="}},{"startdate":"20251129","fullstartdate":"202511290300","enddate":"20251130","url":"/th?id=OHR.DeerVeluwe_PT-BR9808049674_1920x1080.jpg&rf=LaDigue_1920x1080.jpg&pid=hp","urlbase":"/th?id=OHR.DeerVeluwe_PT-BR9808049674","copyright":"Veado-vermelho no Parque Nacional De Hoge Veluwe, Países Baixos (© CreativeNature_nl/Getty Images)","copyrightlink":"/search?q=Parque+Nacional+De+Hoge+Veluwe%2c+Pa%c3%adses+Baixos&form=hpcapt&mkt=pt-br","title":"Coroas na floresta","quiz":"/search?q=Bing+homepage+quiz&filters=WQOskey:%22HPQuiz_20251129_DeerVeluwe%22&FORM=HPQUIZ","wp":true,"hsh":"5ec0d3175f8f9495624acaa20ee55ac5","drk":1,"top":1,"bot":1,"hs":[],"og":{"img":"https://www.bing.com/th?id=OHR.DeerVeluwe_PT-BR9808049674_tmb.jpg","title":"Coroas na floresta","desc":"Veado-vermelho no Parque Nacional De Hoge Veluwe, Países Baixos","hash":"Mdj1D6guhiKikt36eKKGYrmg5vdbjxsfiStpTu1NRa0="}},{"startdate":"20251128","fullstartdate":"202511280300","enddate":"20251129","url":"/th?id=OHR.PraiaFloripa_PT-BR9500409157_1920x1080.jpg&rf=LaDigue_1920x1080.jpg&pid=hp","urlbase":"/th?id=OHR.PraiaFloripa_PT-BR9500409157","copyright":"Praia da Armação, Florianópolis, Santa Catarina (© André Damasco/Getty Images)","copyrightlink":"/search?q=praia+da+arma%c3%a7%c3%a3o+florian%c3%b3polis&form=hpcapt&mkt=pt-br","title":"O som das ondas","quiz":"/search?q=Bing+homepage+quiz&filters=WQOskey:%22HPQuiz_20251128_PraiaFloripa%22&FORM=HPQUIZ","wp":true,"hsh":"4d9c89322c0e884090c3d29b8cf40cfb","drk":1,"top":1,"bot":1,"hs":[],"og":{"img":"https://www.bing.com/th?id=OHR.PraiaFloripa_PT-BR9500409157_tmb.jpg","title":"O som das ondas","desc":"Praia da Armação, Florianópolis, Santa Catarina","hash":"MqltR/A+2baut4xozc3KFw2QvkLzz2m3qaME9hA1oJA="}},{"startdate":"20251127","fullstartdate":"202511270300","enddate":"20251128","url":"/th?id=OHR.PierOfEastbourne2025_PT-BR7338751404_1920x1080.jpg&rf=LaDigue_1920x1080.jpg&pid=hp","urlbase":"/th?id=OHR.PierOfEastbourne2025_PT-BR7338751404","copyright":"Píer de Eastbourne, East Sussex, Inglaterra (© Tolga_TEZCAN/Getty Images)","copyrightlink":"/search?q=Eastbourne+na+Inglaterra&form=hpcapt&mkt=pt-br","title":"Resistência à beira-mar","quiz":"/search?q=Bing+homepage+quiz&filters=WQOskey:%22HPQuiz_20251127_PierOfEastbourne2025%22&FORM=HPQUIZ","wp":true,"hsh":"ea3735b4f1e8a80e04e8ba59e5206ab5","drk":1,"top":1,"bot":1,"hs":[],"og":{"img":"https://www.bing.com/th?id=OHR.PierOfEastbourne2025_PT-BR7338751404_tmb.jpg","title":"Resistência à beira-mar","desc":"Píer de Eastbourne, Inglaterra","hash":"SiMfVrbDzAJlrpYNDxrCJSxUKISXage2s2XxVQl+PiY="}}],"tooltips":{"loading":"Carregando...","previous":"Imagem anterior","next":"Próxima imagem","walle":"Esta imagem não está disponível para ser baixada como papel de parede.","walls":"Baixe esta imagem. O uso desta imagem é restrito ao papel de parede."}}