{"market":{"mkt":"pt-BR"},"images":[{"startdate":"20240326","fullstartdate":"202403260300","enddate":"20240327","url":"/th?id=OHR.HangRaiVietnam_PT-BR9135997938_1920x1080.jpg&rf=LaDigue_1920x1080.jpg&pid=hp","urlbase":"/th?id=OHR.HangRaiVietnam_PT-BR9135997938","copyright":"Cascata de água do mar sobre um antigo recife de coral, Hang Rai, Vietnã (© Thang Tat Nguyen/Getty Images)","copyrightlink":"/search?q=caverna+hang+rai&form=hpcapt&mkt=pt-br","title":"Uma dança da maré","quiz":"/search?q=Bing+homepage+quiz&filters=WQOskey:%22HPQuiz_20240326_HangRaiVietnam%22&FORM=HPQUIZ","wp":true,"hsh":"3e92cd0477d2977f584f95d3686e4d29","drk":1,"top":1,"bot":1,"hs":[],"og":{"img":"https://www.bing.com/th?id=OHR.HangRaiVietnam_PT-BR9135997938_tmb.jpg","title":"Uma dança da maré","desc":"Baía de Vinh Hy, Vietnã","hash":"0eGpisPfzemTv2hhLhLa7IYzzzPAU2WJrDkdE69MNho="}},{"startdate":"20240325","fullstartdate":"202403250300","enddate":"20240326","url":"/th?id=OHR.ColorfulHoli_PT-BR7363563541_1920x1080.jpg&rf=LaDigue_1920x1080.jpg&pid=hp","urlbase":"/th?id=OHR.ColorfulHoli_PT-BR7363563541","copyright":"Devotos hindus brincam com pós coloridos durante o Holi, na Índia (© Avishek Das/SOPA Images/LightRocket via Getty Images)","copyrightlink":"/search?q=Festival+holi&form=hpcapt&mkt=pt-br","title":"Pintando a cidade","quiz":"/search?q=Bing+homepage+quiz&filters=WQOskey:%22HPQuiz_20240325_ColorfulHoli%22&FORM=HPQUIZ","wp":false,"hsh":"cb678c11e83b6bb213dfaddff03d8993","drk":1,"top":1,"bot":1,"hs":[],"og":{"img":"https://www.bing.com/th?id=OHR.ColorfulHoli_PT-BR7363563541_tmb.jpg","title":"Pintando a cidade","desc":"Feliz Holi!","hash":"cIL4jkc1CKsOc6RptDVXYx5iPjKGYC+Qa9cH5ictj04="}},{"startdate":"20240324","fullstartdate":"202403240300","enddate":"20240325","url":"/th?id=OHR.WhiteEyes_PT-BR8910495803_1920x1080.jpg&rf=LaDigue_1920x1080.jpg&pid=hp","urlbase":"/th?id=OHR.WhiteEyes_PT-BR8910495803","copyright":"Ave Silvereyes em um ramo de flor de cerejeira, Coreia do Sul (© TigerSeo/Getty Images)","copyrightlink":"/search?q=Zosterops+lateralis&form=hpcapt&mkt=pt-br","title":"Pode chegar um pouco para lá, por favor?","quiz":"/search?q=Bing+homepage+quiz&filters=WQOskey:%22HPQuiz_20240324_WhiteEyes%22&FORM=HPQUIZ","wp":true,"hsh":"3ecf43ffe9a2a33549739eef28ac6b2c","drk":1,"top":1,"bot":1,"hs":[],"og":{"img":"https://www.bing.com/th?id=OHR.WhiteEyes_PT-BR8910495803_tmb.jpg","title":"Pode chegar um pouco para lá, por favor?","desc":"Ave Silvereyes","hash":"dkwFBKEGlo4KG0w/MDKxZOjuniCggwD/bTJr4VBFl7E="}},{"startdate":"20240323","fullstartdate":"202403230300","enddate":"20240324","url":"/th?id=OHR.ChapadaDiamantinaBahia_PT-BR8776626015_1920x1080.jpg&rf=LaDigue_1920x1080.jpg&pid=hp","urlbase":"/th?id=OHR.ChapadaDiamantinaBahia_PT-BR8776626015","copyright":"Poço encantado em Chapada Diamantina, Bahia (© Cavan Images/Getty Images)","copyrightlink":"/search?q=chapada+diamantina+po%c3%a7os&form=hpcapt&mkt=pt-br","title":"Naturalmente iluminada","quiz":"/search?q=Bing+homepage+quiz&filters=WQOskey:%22HPQuiz_20240323_ChapadaDiamantinaBahia%22&FORM=HPQUIZ","wp":true,"hsh":"e51c2dbb93de2aae3d52d569c8271973","drk":1,"top":1,"bot":1,"hs":[],"og":{"img":"https://www.bing.com/th?id=OHR.ChapadaDiamantinaBahia_PT-BR8776626015_tmb.jpg","title":"Naturalmente iluminada","desc":"Poço Encantado, Chapada Diamantina, Bahia","hash":"VDzxhWF7178JaRkWTHKzIqmCX87QmonYk+uO23P3p4A="}},{"startdate":"20240322","fullstartdate":"202403220300","enddate":"20240323","url":"/th?id=OHR.WaikatoWater_PT-BR9033741044_1920x1080.jpg&rf=LaDigue_1920x1080.jpg&pid=hp","urlbase":"/th?id=OHR.WaikatoWater_PT-BR9033741044","copyright":"Rio Azul, Te Waihou Passagem,Nova Zelândia (© Ian Beattie/Alamy)","copyrightlink":"/search?q=Dia+Mundial+da+%c3%81gua&form=hpcapt&mkt=pt-br","title":"Vamos celebrar a água","quiz":"/search?q=Bing+homepage+quiz&filters=WQOskey:%22HPQuiz_20240322_WaikatoWater%22&FORM=HPQUIZ","wp":true,"hsh":"f721ba7833ad3dfaf1946793ab3ec56b","drk":1,"top":1,"bot":1,"hs":[],"og":{"img":"https://www.bing.com/th?id=OHR.WaikatoWater_PT-BR9033741044_tmb.jpg","title":"Vamos celebrar a água","desc":"Dia Mundial da Água","hash":"dYIKYQdVELEaXcuVSAUFhoAJ8ATOJHtILCzQSMSrVXg="}},{"startdate":"20240321","fullstartdate":"202403210300","enddate":"20240322","url":"/th?id=OHR.BwindiNationalForest_PT-BR3676820157_1920x1080.jpg&rf=LaDigue_1920x1080.jpg&pid=hp","urlbase":"/th?id=OHR.BwindiNationalForest_PT-BR3676820157","copyright":"Floresta Nacional Impenetrável de Bwindi, Uganda (© Art Wolfe/DanitaDelimont.com)","copyrightlink":"/search?q=Dia+International+das+Florestas&form=hpcapt&mkt=pt-br","title":"Tesouros verdes do mundo","quiz":"/search?q=Bing+homepage+quiz&filters=WQOskey:%22HPQuiz_20240321_BwindiNationalForest%22&FORM=HPQUIZ","wp":true,"hsh":"3f8ec5d6d5b43a2140627bdc1022cc95","drk":1,"top":1,"bot":1,"hs":[],"og":{"img":"https://www.bing.com/th?id=OHR.BwindiNationalForest_PT-BR3676820157_tmb.jpg","title":"Tesouros verdes do mundo","desc":"Dia Internacional das Florestas","hash":"E6GgaEIWQHr1C5O1UkIAUxlaMnhOGyMgxfe4gkoWrrQ="}},{"startdate":"20240320","fullstartdate":"202403200300","enddate":"20240321","url":"/th?id=OHR.SpringFrog_PT-BR7201862349_1920x1080.jpg&rf=LaDigue_1920x1080.jpg&pid=hp","urlbase":"/th?id=OHR.SpringFrog_PT-BR7201862349","copyright":"Rã arborícola (© Tetsuya Tanooka/DEEPOL by plainpicture)","copyrightlink":"/search?q=Equin%c3%b3cio+de+outono&form=hpcapt&mkt=pt-br","title":"Entrando no outono","quiz":"/search?q=Bing+homepage+quiz&filters=WQOskey:%22HPQuiz_20240320_SpringFrog%22&FORM=HPQUIZ","wp":true,"hsh":"4d486c3bfc755adeb4dff9b3f01ae503","drk":1,"top":1,"bot":1,"hs":[],"og":{"img":"https://www.bing.com/th?id=OHR.SpringFrog_PT-BR7201862349_tmb.jpg","title":"Entrando no outono","desc":"Equinócio de outono","hash":"5T1QPaIvXHURlD05KwdIykkk9CxJRdVu39VoREC1yak="}},{"startdate":"20240319","fullstartdate":"202403190300","enddate":"20240320","url":"/th?id=OHR.SpringCaveDale_PT-BR8455080776_1920x1080.jpg&rf=LaDigue_1920x1080.jpg&pid=hp","urlbase":"/th?id=OHR.SpringCaveDale_PT-BR8455080776","copyright":"Cave Dale e Castelo de Peveril em Castleton, Parque Nacional de Peak District, Derbyshire, Inglaterra (© James Osmond/Alamy)","copyrightlink":"/search?q=Castelo+de+Peveril+&form=hpcapt&mkt=pt-br","title":"Uma caminhada pelo desfiladeiro","quiz":"/search?q=Bing+homepage+quiz&filters=WQOskey:%22HPQuiz_20240319_SpringCaveDale%22&FORM=HPQUIZ","wp":true,"hsh":"5543f5ec1de54ce90cf7e9617904ded0","drk":1,"top":1,"bot":1,"hs":[],"og":{"img":"https://www.bing.com/th?id=OHR.SpringCaveDale_PT-BR8455080776_tmb.jpg","title":"Uma caminhada pelo desfiladeiro","desc":"Cave Dale e Castelo de Peveril, Derbyshire, Inglaterra","hash":"n+qAezzTyg2KESVVbl9xh7qKXWJF6iFzC+3iEauaAWA="}}],"tooltips":{"loading":"Carregando...","previous":"Imagem anterior","next":"Próxima imagem","walle":"Esta imagem não está disponível para ser baixada como papel de parede.","walls":"Baixe esta imagem. O uso desta imagem é restrito ao papel de parede."}}