{"market":{"mkt":"pt-BR"},"images":[{"startdate":"20250801","fullstartdate":"202508010300","enddate":"20250802","url":"/th?id=OHR.EdinburghFringe_PT-BR1616898906_1920x1080.jpg&rf=LaDigue_1920x1080.jpg&pid=hp","urlbase":"/th?id=OHR.EdinburghFringe_PT-BR1616898906","copyright":"Royal Mile, Edimburgo, Escócia (© MEDITERRANEAN/Getty Images)","copyrightlink":"/search?q=Festival+Fringe+de+Edimburgo&form=hpcapt&mkt=pt-br","title":"Espere o inesperado!","quiz":"/search?q=Bing+homepage+quiz&filters=WQOskey:%22HPQuiz_20250801_EdinburghFringe%22&FORM=HPQUIZ","wp":true,"hsh":"57411ff93437eeb67e0bf044f1bf9e50","drk":1,"top":1,"bot":1,"hs":[],"og":{"img":"https://www.bing.com/th?id=OHR.EdinburghFringe_PT-BR1616898906_tmb.jpg","title":"Espere o inesperado!","desc":"Festival Fringe de Edimburgo","hash":"42QR90BzDPG/6WXB/9CP6OevVLnevNTIm7LAyvmO268="}},{"startdate":"20250731","fullstartdate":"202507310300","enddate":"20250801","url":"/th?id=OHR.NaPaliKauai_PT-BR1647941765_1920x1080.jpg&rf=LaDigue_1920x1080.jpg&pid=hp","urlbase":"/th?id=OHR.NaPaliKauai_PT-BR1647941765","copyright":"Praia de Kalalau na Costa Nā Pali, Kauai, Havaí, EUA (© Russ Bishop/DanitaDelimont.com)","copyrightlink":"/search?q=Kauai+no+Hava%c3%ad&form=hpcapt&mkt=pt-br","title":"Desconectado da rede","quiz":"/search?q=Bing+homepage+quiz&filters=WQOskey:%22HPQuiz_20250731_NaPaliKauai%22&FORM=HPQUIZ","wp":true,"hsh":"f20577d5662753e701d05c5681acd50f","drk":1,"top":1,"bot":1,"hs":[],"og":{"img":"https://www.bing.com/th?id=OHR.NaPaliKauai_PT-BR1647941765_tmb.jpg","title":"Desconectado da rede","desc":"Praia de Kalalau, Costa Nā Pali, Kauai, Havaí, EUA","hash":"zn62fK8KxSCoc3na9T3gYjD6fy2POJBfvo3lb5C3Dx4="}},{"startdate":"20250730","fullstartdate":"202507300300","enddate":"20250731","url":"/th?id=OHR.SaypeDubai_PT-BR3110184128_1920x1080.jpg&rf=LaDigue_1920x1080.jpg&pid=hp","urlbase":"/th?id=OHR.SaypeDubai_PT-BR3110184128","copyright":"Instalação de arte \"Beyond Walls\", de Saype, na Expo 2020 Dubai, Emirados Árabes Unidos (© VALENTIN FLAURAUD/EPA-EFE/Shutterstock)","copyrightlink":"/search?q=Dia+Internacional+da+Amizade&form=hpcapt&mkt=pt-br","title":"Amizade sem fronteiras","quiz":"/search?q=Bing+homepage+quiz&filters=WQOskey:%22HPQuiz_20250730_SaypeDubai%22&FORM=HPQUIZ","wp":false,"hsh":"71f85a8290ebe512f50298d748597391","drk":1,"top":1,"bot":1,"hs":[],"og":{"img":"https://www.bing.com/th?id=OHR.SaypeDubai_PT-BR3110184128_tmb.jpg","title":"Amizade sem fronteiras","desc":"Dia Internacional da Amizade","hash":"uugFRbOoIlfCwPDOiCWrId13lmWUGiqzTp4qXd0Dt9E="}},{"startdate":"20250729","fullstartdate":"202507290300","enddate":"20250730","url":"/th?id=OHR.TigerDay_PT-BR9994663817_1920x1080.jpg&rf=LaDigue_1920x1080.jpg&pid=hp","urlbase":"/th?id=OHR.TigerDay_PT-BR9994663817","copyright":"Tigre-de-bengala fêmea, Parque Nacional de Kanha, Índia (© Axel Gomille/Nature Picture Library)","copyrightlink":"/search?q=Dia+Internacional+do+Tigre&form=hpcapt&mkt=pt-br","title":"A rainha da selva","quiz":"/search?q=Bing+homepage+quiz&filters=WQOskey:%22HPQuiz_20250729_TigerDay%22&FORM=HPQUIZ","wp":true,"hsh":"6fbfefa768364fc9ae6abc768c5d422d","drk":1,"top":1,"bot":1,"hs":[],"og":{"img":"https://www.bing.com/th?id=OHR.TigerDay_PT-BR9994663817_tmb.jpg","title":"A rainha da selva","desc":"Dia Internacional do Tigre","hash":"ei1sCb7AJejMY/PjTYOwTWM7fjPIuKKbcPfMTEPbtfo="}},{"startdate":"20250728","fullstartdate":"202507280300","enddate":"20250729","url":"/th?id=OHR.MongoliaYurts_PT-BR1789497655_1920x1080.jpg&rf=LaDigue_1920x1080.jpg&pid=hp","urlbase":"/th?id=OHR.MongoliaYurts_PT-BR1789497655","copyright":"Yurts nas planícies da Mongólia (© Michel Arnault/Shutterstock)","copyrightlink":"/search?q=Dia+Mundial+da+Conserva%c3%a7%c3%a3o+da+Natureza&form=hpcapt&mkt=pt-br","title":"Conservar é viver","quiz":"/search?q=Bing+homepage+quiz&filters=WQOskey:%22HPQuiz_20250728_MongoliaYurts%22&FORM=HPQUIZ","wp":true,"hsh":"e21b180bf325fba7a8b33ac917e64a18","drk":1,"top":1,"bot":1,"hs":[],"og":{"img":"https://www.bing.com/th?id=OHR.MongoliaYurts_PT-BR1789497655_tmb.jpg","title":"Conservar é viver","desc":"Dia Mundial da Conservação da Natureza","hash":"axACPN8UMbVQ8fFetWSVFfRK2jHIm2e2tEzaveOAx7s="}},{"startdate":"20250727","fullstartdate":"202507270300","enddate":"20250728","url":"/th?id=OHR.BlackfinBarracuda_PT-BR7423945711_1920x1080.jpg&rf=LaDigue_1920x1080.jpg&pid=hp","urlbase":"/th?id=OHR.BlackfinBarracuda_PT-BR7423945711","copyright":"Cardume de barracudas-de-barbatana-preta, Shark Reef, Parque Nacional Ras Mohammed, Península do Sinai, Egito (© Alex Mustard/Nature Picture Library)","copyrightlink":"/search?q=Parque+Nacional+Ras+Mohammed%2c+Pen%c3%adnsula+do+Sinai%2c+Egito&form=hpcapt&mkt=pt-br","title":"Brilho em sincronia","quiz":"/search?q=Bing+homepage+quiz&filters=WQOskey:%22HPQuiz_20250727_BlackfinBarracuda%22&FORM=HPQUIZ","wp":true,"hsh":"aef7212ae95ca5babead8fc8b67b28e9","drk":1,"top":1,"bot":1,"hs":[],"og":{"img":"https://www.bing.com/th?id=OHR.BlackfinBarracuda_PT-BR7423945711_tmb.jpg","title":"Brilho em sincronia","desc":"Barracudas-de-barbatana-preta, Parque Nacional Ras Mohammed, Sinai, Egito","hash":"nTx6WHnyZPgVOKxxWaXF77mz6h3F6ujidLJMy2Mltfo="}},{"startdate":"20250726","fullstartdate":"202507260300","enddate":"20250727","url":"/th?id=OHR.MangroveTwilight_PT-BR1374948765_1920x1080.jpg&rf=LaDigue_1920x1080.jpg&pid=hp","urlbase":"/th?id=OHR.MangroveTwilight_PT-BR1374948765","copyright":"Manguezais ao entardecer, Praia de Walakiri, ilha de Sumba, Indonésia (© Boonchet Ch./Getty Images)","copyrightlink":"/search?q=Dia+Mundial+de+Prote%c3%a7%c3%a3o+aos+Manguezais&form=hpcapt&mkt=pt-br","title":"Sentinelas da maré","quiz":"/search?q=Bing+homepage+quiz&filters=WQOskey:%22HPQuiz_20250726_MangroveTwilight%22&FORM=HPQUIZ","wp":true,"hsh":"5d4730f4a59ee55b076db6aa97f46acc","drk":1,"top":1,"bot":1,"hs":[],"og":{"img":"https://www.bing.com/th?id=OHR.MangroveTwilight_PT-BR1374948765_tmb.jpg","title":"Sentinelas da maré","desc":"Dia Mundial de Proteção aos Manguezais","hash":"W5Z5B1Gi/j+nU+LhJY9+UwWwonIec6vHdK8BzemVOwg="}},{"startdate":"20250725","fullstartdate":"202507250300","enddate":"20250726","url":"/th?id=OHR.LasPalmas_PT-BR7218640401_1920x1080.jpg&rf=LaDigue_1920x1080.jpg&pid=hp","urlbase":"/th?id=OHR.LasPalmas_PT-BR7218640401","copyright":"Vista aérea das casas coloridas em Palmas da Grã-Canária, Espanha (© Marco Bottigelli/Getty Images)","copyrightlink":"/search?q=Palmas+da+Gr%c3%a3-Can%c3%a1ria&form=hpcapt&mkt=pt-br","title":"Tela da vida","quiz":"/search?q=Bing+homepage+quiz&filters=WQOskey:%22HPQuiz_20250725_LasPalmas%22&FORM=HPQUIZ","wp":true,"hsh":"c1ebdc2e994d98d421b6db57407683e1","drk":1,"top":1,"bot":1,"hs":[],"og":{"img":"https://www.bing.com/th?id=OHR.LasPalmas_PT-BR7218640401_tmb.jpg","title":"Tela da vida","desc":"Casas coloridas, Palmas da Grã-Canária, Espanha","hash":"+W3NdWyes077YgiEuVx83mC6zhudRM3s1nczdoSRN2Y="}}],"tooltips":{"loading":"Carregando...","previous":"Imagem anterior","next":"Próxima imagem","walle":"Esta imagem não está disponível para ser baixada como papel de parede.","walls":"Baixe esta imagem. O uso desta imagem é restrito ao papel de parede."}}