{"market":{"mkt":"nl-NL"},"images":[{"startdate":"20240830","fullstartdate":"202408300700","enddate":"20240831","url":"/th?id=OHR.WhaleSharkDay_ROW6113482072_1920x1080.jpg&rf=LaDigue_1920x1080.jpg&pid=hp","urlbase":"/th?id=OHR.WhaleSharkDay_ROW6113482072","copyright":"A whale shark in Cenderawasih Bay, West Papua, Indonesia (© Andy Lerner/Tandem Stills + Motion)","copyrightlink":"/search?q=Whale+sharks&form=hpcapt","title":"Info","quiz":"/search?q=Bing+homepage+quiz&filters=WQOskey:%22HPQuiz_20240830_WhaleSharkDay%22&FORM=HPQUIZ","wp":true,"hsh":"da6513095567c1f91e80636d38e32bdf","drk":1,"top":1,"bot":1,"hs":[],"og":{"img":"https://www.bing.com/th?id=OHR.WhaleSharkDay_ROW6113482072_tmb.jpg","title":"Info","desc":"Whale shark","hash":"IdBc7dLJGNRmI+SQO2xbQ/ajg2vvbE3HhOVr3XHYFVo="}},{"startdate":"20240829","fullstartdate":"202408290700","enddate":"20240830","url":"/th?id=OHR.CastellfollitSpain_ROW5434874664_1920x1080.jpg&rf=LaDigue_1920x1080.jpg&pid=hp","urlbase":"/th?id=OHR.CastellfollitSpain_ROW5434874664","copyright":"Castellfollit de la Roca, Catalonia, Spain (© Eloi_Omella/Getty Images)","copyrightlink":"/search?q=Castellfollit+de+la+Roca+Spain&form=hpcapt","title":"Info","quiz":"/search?q=Bing+homepage+quiz&filters=WQOskey:%22HPQuiz_20240829_CastellfollitSpain%22&FORM=HPQUIZ","wp":true,"hsh":"f99e3c5822b9631cd1f4fa20c6d55890","drk":1,"top":1,"bot":1,"hs":[],"og":{"img":"https://www.bing.com/th?id=OHR.CastellfollitSpain_ROW5434874664_tmb.jpg","title":"Info","desc":"Castellfollit de la Roca, Catalonia, Spain","hash":"HgRo+qJE9R02pAUJh5INZXtLxU6gunkbCgC29N6ZLw4="}},{"startdate":"20240828","fullstartdate":"202408280700","enddate":"20240829","url":"/th?id=OHR.ParalympicsParis_ROW1372193453_1920x1080.jpg&rf=LaDigue_1920x1080.jpg&pid=hp","urlbase":"/th?id=OHR.ParalympicsParis_ROW1372193453","copyright":"Montmartre and Sacre Cœur, Paris, France (© Tuul & Bruno Morandi/Getty Images)","copyrightlink":"/search?q=Montmartre+and+Sacre+C%c5%93ur&form=hpcapt","title":"Info","quiz":"/search?q=Bing+homepage+quiz&filters=WQOskey:%22HPQuiz_20240828_ParalympicsParis%22&FORM=HPQUIZ","wp":true,"hsh":"6d11c6bea9ff5c5d5a43e751bb0aab4f","drk":1,"top":1,"bot":1,"hs":[],"og":{"img":"https://www.bing.com/th?id=OHR.ParalympicsParis_ROW1372193453_tmb.jpg","title":"Info","desc":"Sacré-Cœur Basilica, Paris","hash":"XT231XxQeKoQxRG+6VlDUAIdev3hzPp4HRG9f8QMqKg="}},{"startdate":"20240827","fullstartdate":"202408270700","enddate":"20240828","url":"/th?id=OHR.YoungCaiman_ROW5014887226_1920x1080.jpg&rf=LaDigue_1920x1080.jpg&pid=hp","urlbase":"/th?id=OHR.YoungCaiman_ROW5014887226","copyright":"Young black caiman, Tambopata National Reserve, Peru (© Maxime Aliaga/Minden Pictures)","copyrightlink":"/search?q=Black+caiman&form=hpcapt","title":"Info","quiz":"/search?q=Bing+homepage+quiz&filters=WQOskey:%22HPQuiz_20240827_YoungCaiman%22&FORM=HPQUIZ","wp":true,"hsh":"a50c9c76de7104340fde38cf88f2ebc0","drk":1,"top":1,"bot":1,"hs":[],"og":{"img":"https://www.bing.com/th?id=OHR.YoungCaiman_ROW5014887226_tmb.jpg","title":"Info","desc":"Young black caiman","hash":"eCzTIXmkkk010Qb7MWTnhkt4wMHlLWr3EeQGRV73EA0="}},{"startdate":"20240826","fullstartdate":"202408260700","enddate":"20240827","url":"/th?id=OHR.PalmyraAtoll_ROW4852915271_1920x1080.jpg&rf=LaDigue_1920x1080.jpg&pid=hp","urlbase":"/th?id=OHR.PalmyraAtoll_ROW4852915271","copyright":"Palmyra Atoll National Wildlife Refuge, Central Pacific Ocean (© Ian Shive/Tandem Stills + Motion)","copyrightlink":"/search?q=Palmyra+Atoll&form=hpcapt","title":"Info","quiz":"/search?q=Bing+homepage+quiz&filters=WQOskey:%22HPQuiz_20240826_PalmyraAtoll%22&FORM=HPQUIZ","wp":true,"hsh":"2d7b89ddea9791ce6e1b307b7937cc1b","drk":1,"top":1,"bot":1,"hs":[],"og":{"img":"https://www.bing.com/th?id=OHR.PalmyraAtoll_ROW4852915271_tmb.jpg","title":"Info","desc":"Palmyra Atoll National Wildlife Refuge","hash":"2zwjk1Wf0MH2H0obsQKIreS2VO3wbY18I0sMigz9uQ4="}},{"startdate":"20240825","fullstartdate":"202408250700","enddate":"20240826","url":"/th?id=OHR.SwiftcurrentLake_ROW4729110075_1920x1080.jpg&rf=LaDigue_1920x1080.jpg&pid=hp","urlbase":"/th?id=OHR.SwiftcurrentLake_ROW4729110075","copyright":"Sunrise over Swiftcurrent Lake, Glacier National Park, Montana (© Jason Savage/Tandem Stills + Motion)","copyrightlink":"/search?q=Swiftcurrent+Lake&form=hpcapt","title":"Info","quiz":"/search?q=Bing+homepage+quiz&filters=WQOskey:%22HPQuiz_20240825_SwiftcurrentLake%22&FORM=HPQUIZ","wp":true,"hsh":"026206da976ec417724351d9bab513b2","drk":1,"top":1,"bot":1,"hs":[],"og":{"img":"https://www.bing.com/th?id=OHR.SwiftcurrentLake_ROW4729110075_tmb.jpg","title":"Info","desc":"Glacier National Park, Montana","hash":"UqSpXARGi2CLl+GfCyXG6y5ywOzlpnTnHl6VQZGe+1g="}},{"startdate":"20240824","fullstartdate":"202408240700","enddate":"20240825","url":"/th?id=OHR.KatahdinWoods_ROW4600559064_1920x1080.jpg&rf=LaDigue_1920x1080.jpg&pid=hp","urlbase":"/th?id=OHR.KatahdinWoods_ROW4600559064","copyright":"Katahdin Woods and Waters National Monument, Penobscot County, Maine (© Cavan Images/Alamy)","copyrightlink":"/search?q=Katahdin+Woods+and+Waters+National+Monument&form=hpcapt","title":"Info","quiz":"/search?q=Bing+homepage+quiz&filters=WQOskey:%22HPQuiz_20240824_KatahdinWoods%22&FORM=HPQUIZ","wp":true,"hsh":"de8e87087e4a1f722da545151cc5b67c","drk":1,"top":1,"bot":1,"hs":[],"og":{"img":"https://www.bing.com/th?id=OHR.KatahdinWoods_ROW4600559064_tmb.jpg","title":"Info","desc":"Katahdin Woods and Waters National Monument, USA","hash":"tyCX6AtlbvuvSSOH4ENExNhVPTGE1HSIpFjpYFQTL1Q="}},{"startdate":"20240823","fullstartdate":"202408230700","enddate":"20240824","url":"/th?id=OHR.PrasatPhanom_ROW3985058133_1920x1080.jpg&rf=LaDigue_1920x1080.jpg&pid=hp","urlbase":"/th?id=OHR.PrasatPhanom_ROW3985058133","copyright":"Prasat Phanom Rung temple ruins, Buriram province, Thailand (© Banjongseal324/Getty Images)","copyrightlink":"/search?q=Phanom+Rung+Historical+Park&form=hpcapt","title":"Info","quiz":"/search?q=Bing+homepage+quiz&filters=WQOskey:%22HPQuiz_20240823_PrasatPhanom%22&FORM=HPQUIZ","wp":true,"hsh":"e9fb5ad452241e63aa9660c3cfe156ac","drk":1,"top":1,"bot":1,"hs":[],"og":{"img":"https://www.bing.com/th?id=OHR.PrasatPhanom_ROW3985058133_tmb.jpg","title":"Info","desc":"Prasat Phanom Rung temple ruins, Thailand","hash":"qe7rZhMVhhSFsvae5fqYAXHpDDA3KWoH/Hebz9g0oDY="}}],"tooltips":{"loading":"Laden...","previous":"Vorige afbeelding","next":"Volgende afbeelding","walle":"Deze afbeelding kan niet worden gedownload als bureaubladachtergrond.","walls":"Download deze afbeelding. U mag deze afbeelding alleen gebruiken als achtergrond."}}