{"market":{"mkt":"sv-SE"},"images":[{"startdate":"20250318","fullstartdate":"202503180700","enddate":"20250319","url":"/th?id=OHR.SedonaSpring_ROW7606994452_1920x1080.jpg&rf=LaDigue_1920x1080.jpg&pid=hp","urlbase":"/th?id=OHR.SedonaSpring_ROW7606994452","copyright":"Red rock formations, Sedona, Arizona, United States (© Jim Ekstrand/Alamy Stock Photo)","copyrightlink":"/search?q=sedona+arizona&form=hpcapt","title":"Info","quiz":"/search?q=Bing+homepage+quiz&filters=WQOskey:%22HPQuiz_20250318_SedonaSpring%22&FORM=HPQUIZ","wp":true,"hsh":"f9af32332cd285d4e45516679ea6d3c7","drk":1,"top":1,"bot":1,"hs":[],"og":{"img":"https://www.bing.com/th?id=OHR.SedonaSpring_ROW7606994452_tmb.jpg","title":"Info","desc":"Red Rocks, Sedona, Arizona, United States","hash":"+dWlK3FaFaFFzEw02dVCwIck2svhks7eoxQvYyLYNgI="}},{"startdate":"20250317","fullstartdate":"202503170700","enddate":"20250318","url":"/th?id=OHR.BeckettBridge_ROW7629520157_1920x1080.jpg&rf=LaDigue_1920x1080.jpg&pid=hp","urlbase":"/th?id=OHR.BeckettBridge_ROW7629520157","copyright":"Samuel Beckett Bridge, Dublin, Ireland (© Colm Keating/Tandem Stills + Motion)","copyrightlink":"/search?q=Samuel+Beckett+Bridge&form=hpcapt","title":"Info","quiz":"/search?q=Bing+homepage+quiz&filters=WQOskey:%22HPQuiz_20250317_BeckettBridge%22&FORM=HPQUIZ","wp":true,"hsh":"dec514fe5446c2dc6f22072acb166ce1","drk":1,"top":1,"bot":1,"hs":[],"og":{"img":"https://www.bing.com/th?id=OHR.BeckettBridge_ROW7629520157_tmb.jpg","title":"Info","desc":"Samuel Beckett Bridge, Dublin, Ireland","hash":"0C/ICYLN4Hhw/Penl1kQVq9Pd14rnF34AjNPcKRyAYU="}},{"startdate":"20250316","fullstartdate":"202503160700","enddate":"20250317","url":"/th?id=OHR.BigGardenBirdwatch2025_ROW7653300959_1920x1080.jpg&rf=LaDigue_1920x1080.jpg&pid=hp","urlbase":"/th?id=OHR.BigGardenBirdwatch2025_ROW7653300959","copyright":"A kingfisher perched on a branch (© NJphoto/Alamy)","copyrightlink":"/search?q=Kingfisher&form=hpcapt","title":"Info","quiz":"/search?q=Bing+homepage+quiz&filters=WQOskey:%22HPQuiz_20250316_BigGardenBirdwatch2025%22&FORM=HPQUIZ","wp":true,"hsh":"0bef1bac66ffb0599c7252190db61e2b","drk":1,"top":1,"bot":1,"hs":[],"og":{"img":"https://www.bing.com/th?id=OHR.BigGardenBirdwatch2025_ROW7653300959_tmb.jpg","title":"Info","desc":"A kingfisher perched on a branch","hash":"F80idAfv85sV3+POlfTb8rRqUBzlCmkLRLlYNAEywy8="}},{"startdate":"20250315","fullstartdate":"202503150700","enddate":"20250316","url":"/th?id=OHR.ForumRomanum_ROW7684301989_1920x1080.jpg&rf=LaDigue_1920x1080.jpg&pid=hp","urlbase":"/th?id=OHR.ForumRomanum_ROW7684301989","copyright":"The Temple of Saturn in the Roman Forum, Rome, Italy (© Nico De Pasquale Photography/Getty Images)","copyrightlink":"/search?q=The+Temple+of+Saturn&form=hpcapt","title":"Info","quiz":"/search?q=Bing+homepage+quiz&filters=WQOskey:%22HPQuiz_20250315_ForumRomanum%22&FORM=HPQUIZ","wp":true,"hsh":"a3e3040fe0e07aeb20cd93ddb1f79561","drk":1,"top":1,"bot":1,"hs":[],"og":{"img":"https://www.bing.com/th?id=OHR.ForumRomanum_ROW7684301989_tmb.jpg","title":"Info","desc":"The Temple of Saturn, Rome, Italy","hash":"HtFlLYLsyLCQ6MBLLNydOz+RFRHPOQhhfyad7efoTDk="}},{"startdate":"20250314","fullstartdate":"202503140700","enddate":"20250315","url":"/th?id=OHR.BasqueDolmen_ROW7711296740_1920x1080.jpg&rf=LaDigue_1920x1080.jpg&pid=hp","urlbase":"/th?id=OHR.BasqueDolmen_ROW7711296740","copyright":"Dolmen of Sorginetxe, Basque Country, Alava, Spain (© David Herraez Calzada/plainpicture)","copyrightlink":"/search?q=Dolmen+of+Sorginetxe&form=hpcapt","title":"Info","quiz":"/search?q=Bing+homepage+quiz&filters=WQOskey:%22HPQuiz_20250314_BasqueDolmen%22&FORM=HPQUIZ","wp":true,"hsh":"11beb831e062507dde9966c7311c9fe6","drk":1,"top":1,"bot":1,"hs":[],"og":{"img":"https://www.bing.com/th?id=OHR.BasqueDolmen_ROW7711296740_tmb.jpg","title":"Info","desc":"Dolmen of Sorginetxe, Spain","hash":"T7+hq6Ce75Bp49ubHLGfTBH3nIV/7S1jHliS3nf5ugo="}},{"startdate":"20250313","fullstartdate":"202503130700","enddate":"20250314","url":"/th?id=OHR.Piedmont_ROW7537490150_1920x1080.jpg&rf=LaDigue_1920x1080.jpg&pid=hp","urlbase":"/th?id=OHR.Piedmont_ROW7537490150","copyright":"Gran Paradiso National Park, Piedmont, Italy (© Stefano Zaccaria/Alamy)","copyrightlink":"/search?q=Gran+Paradiso+National+Park&form=hpcapt","title":"Info","quiz":"/search?q=Bing+homepage+quiz&filters=WQOskey:%22HPQuiz_20250313_Piedmont%22&FORM=HPQUIZ","wp":true,"hsh":"a31bfc43b0bfa4db6cf1db13ba4fe8d2","drk":1,"top":1,"bot":1,"hs":[],"og":{"img":"https://www.bing.com/th?id=OHR.Piedmont_ROW7537490150_tmb.jpg","title":"Info","desc":"Gran Paradiso National Park, Piedmont, Italy","hash":"2PW6YAQxyPYxPk5/kE+j+6EXq2NImSjfC75jMDcY4BU="}},{"startdate":"20250312","fullstartdate":"202503120700","enddate":"20250313","url":"/th?id=OHR.ChateauLoire_ROW0522762905_1920x1080.jpg&rf=LaDigue_1920x1080.jpg&pid=hp","urlbase":"/th?id=OHR.ChateauLoire_ROW0522762905","copyright":"Château de Sully-sur-Loire, Centre-Val de Loire, France (© StockPhotoAstur/Shutterstock)","copyrightlink":"/search?q=Sully+sur+Loire+chateau&form=hpcapt","title":"Info","quiz":"/search?q=Bing+homepage+quiz&filters=WQOskey:%22HPQuiz_20250312_ChateauLoire%22&FORM=HPQUIZ","wp":true,"hsh":"c7e5e0f50d133d2552161ff4d24ec125","drk":1,"top":1,"bot":1,"hs":[],"og":{"img":"https://www.bing.com/th?id=OHR.ChateauLoire_ROW0522762905_tmb.jpg","title":"Info","desc":"Château de Sully-sur-Loire, Centre-Val de Loire, France","hash":"ifXZlL3su/pMHTjUGgIAnKpfxfLUTT1RDXL72hccMZ4="}},{"startdate":"20250311","fullstartdate":"202503110700","enddate":"20250312","url":"/th?id=OHR.NusaPenida_ROW7505183112_1920x1080.jpg&rf=LaDigue_1920x1080.jpg&pid=hp","urlbase":"/th?id=OHR.NusaPenida_ROW7505183112","copyright":"Broken Beach in Nusa Penida, Bali, Indonesia (© joakimbkk/Getty Images)","copyrightlink":"/search?q=Nusa+Penida+Island&form=hpcapt","title":"Info","quiz":"/search?q=Bing+homepage+quiz&filters=WQOskey:%22HPQuiz_20250311_NusaPenida%22&FORM=HPQUIZ","wp":true,"hsh":"aa89617b046465c0642915fc389f7470","drk":1,"top":1,"bot":1,"hs":[],"og":{"img":"https://www.bing.com/th?id=OHR.NusaPenida_ROW7505183112_tmb.jpg","title":"Info","desc":"Broken Beach in Nusa Penida, Bali, Indonesia","hash":"h9D0i/131JkzP9FtpPJOJuy7Dq2XM0suaMn8Pb5UIBg="}}],"tooltips":{"loading":"Läser in...","previous":"Föregående bild","next":"Nästa bild","walle":"Den här bilden finns inte tillgänglig att ladda ner som skrivbordsbild.","walls":"Hämta den här bilden. Bilden får endast användas som skrivbordsunderlägg."}}