{"market":{"mkt":"ko-KR"},"images":[{"startdate":"20240714","fullstartdate":"202407140700","enddate":"20240715","url":"/th?id=OHR.LaGeriaLanzarote_ROW1086932756_1920x1080.jpg&rf=LaDigue_1920x1080.jpg&pid=hp","urlbase":"/th?id=OHR.LaGeriaLanzarote_ROW1086932756","copyright":"Volcanic vineyard in the La Geria wine region of Lanzarote, Canary Islands, Spain (© Pol Albarrán/Getty Images)","copyrightlink":"/search?q=Lanzarote+island+Spain&form=hpcapt","title":"Info","quiz":"/search?q=Bing+homepage+quiz&filters=WQOskey:%22HPQuiz_20240714_LaGeriaLanzarote%22&FORM=HPQUIZ","wp":true,"hsh":"7e3544b6ecd2aaf2d45d0ff3c3dce619","drk":1,"top":1,"bot":1,"hs":[],"og":{"img":"https://www.bing.com/th?id=OHR.LaGeriaLanzarote_ROW1086932756_tmb.jpg","title":"Info","desc":"La Geria wine region, Lanzarote, Canary Islands, Spain","hash":"zR1bx6SOsSRE/Rb6EEXfibFuvUvPgMsg6rcJ3nsypX4="}},{"startdate":"20240713","fullstartdate":"202407130700","enddate":"20240714","url":"/th?id=OHR.CappadociaRocks_ROW0377165028_1920x1080.jpg&rf=LaDigue_1920x1080.jpg&pid=hp","urlbase":"/th?id=OHR.CappadociaRocks_ROW0377165028","copyright":"Fairy chimneys and cave dwellings in Cappadocia, Türkiye (© Storm Is Me/Shutterstock)","copyrightlink":"/search?q=Cappadocia+Turkey&form=hpcapt","title":"Info","quiz":"/search?q=Bing+homepage+quiz&filters=WQOskey:%22HPQuiz_20240713_CappadociaRocks%22&FORM=HPQUIZ","wp":true,"hsh":"d52fba6574101de8974afc6db0524476","drk":1,"top":1,"bot":1,"hs":[],"og":{"img":"https://www.bing.com/th?id=OHR.CappadociaRocks_ROW0377165028_tmb.jpg","title":"Info","desc":"Fairy chimneys and cave dwellings in Cappadocia, Türkiye","hash":"FH4f3/ciThmIPXhaOSOfJrm4YXsJYbKszUvLDAFyJaI="}},{"startdate":"20240712","fullstartdate":"202407120700","enddate":"20240713","url":"/th?id=OHR.RainierWildflowers_ROW0723868110_1920x1080.jpg&rf=LaDigue_1920x1080.jpg&pid=hp","urlbase":"/th?id=OHR.RainierWildflowers_ROW0723868110","copyright":"Wildflowers in Mount Rainier National Park, Washington (© RomanKhomlyak/Getty Images)","copyrightlink":"/search?q=Mount+Rainier+National+Park&form=hpcapt","title":"Info","quiz":"/search?q=Bing+homepage+quiz&filters=WQOskey:%22HPQuiz_20240712_RainierWildflowers%22&FORM=HPQUIZ","wp":true,"hsh":"28c026575dc52bab34a8d9b0944a7e6b","drk":1,"top":1,"bot":1,"hs":[],"og":{"img":"https://www.bing.com/th?id=OHR.RainierWildflowers_ROW0723868110_tmb.jpg","title":"Info","desc":"Mount Rainier National Park, Washington, USA","hash":"HU9WGnux+VeMu/IO6ZJdi9jQcncE5Eho9bAv6nofZ3Q="}},{"startdate":"20240711","fullstartdate":"202407110700","enddate":"20240712","url":"/th?id=OHR.GangiSicily_ROW7478638789_1920x1080.jpg&rf=LaDigue_1920x1080.jpg&pid=hp","urlbase":"/th?id=OHR.GangiSicily_ROW7478638789","copyright":"Gangi, Sicily, Italy (© Andrea Caruso/Amazing Aerial Agency)","copyrightlink":"/search?q=Gangi+Sicily+Italy","title":"Info","quiz":"/search?q=Bing+homepage+quiz&filters=WQOskey:%22HPQuiz_20240711_GangiSicily%22&FORM=HPQUIZ","wp":true,"hsh":"46efa32acdf74f11c76931be03acfc60","drk":1,"top":1,"bot":1,"hs":[],"og":{"img":"https://www.bing.com/th?id=OHR.GangiSicily_ROW7478638789_tmb.jpg","title":"Info","desc":"Gangi, Sicily, Italy","hash":"TjOTzOnuUTofPWN4xlJoAHcCfy60+RE510DYU61ogvo="}},{"startdate":"20240710","fullstartdate":"202407100700","enddate":"20240711","url":"/th?id=OHR.CollaredAracari_ROW9660042641_1920x1080.jpg&rf=LaDigue_1920x1080.jpg&pid=hp","urlbase":"/th?id=OHR.CollaredAracari_ROW9660042641","copyright":"Collared aracari, Costa Rica (© Juan Carlos Vindas/Getty Images)","copyrightlink":"/search?q=Collared+Aracari&form=hpcapt","title":"Info","quiz":"/search?q=Bing+homepage+quiz&filters=WQOskey:%22HPQuiz_20240710_CollaredAracari%22&FORM=HPQUIZ","wp":true,"hsh":"65d92130f6208f55f0c7a38c19a3a481","drk":1,"top":1,"bot":1,"hs":[],"og":{"img":"https://www.bing.com/th?id=OHR.CollaredAracari_ROW9660042641_tmb.jpg","title":"Info","desc":"Collared aracari","hash":"lNOD7Oi9T85/s5E4xFodq0f3L6hEeT3MdieIHLaxCok="}},{"startdate":"20240709","fullstartdate":"202407090700","enddate":"20240710","url":"/th?id=OHR.TalampayaNP_ROW6737136981_1920x1080.jpg&rf=LaDigue_1920x1080.jpg&pid=hp","urlbase":"/th?id=OHR.TalampayaNP_ROW6737136981","copyright":"Talampaya National Park, La Rioja province, Argentina (© Gonzalo Azumendi/Getty Images)","copyrightlink":"/search?q=Talampaya+National+Park+Argentina&form=hpcapt","title":"Info","quiz":"/search?q=Bing+homepage+quiz&filters=WQOskey:%22HPQuiz_20240709_TalampayaNP%22&FORM=HPQUIZ","wp":true,"hsh":"e8fd6ebd313def7eacf8783fb152b7d2","drk":1,"top":1,"bot":1,"hs":[],"og":{"img":"https://www.bing.com/th?id=OHR.TalampayaNP_ROW6737136981_tmb.jpg","title":"Info","desc":"Talampaya National Park, Argentina","hash":"j3FqyD/Se+H8jmfgAq2YzS7yL9xmWlNv6Zf7Dm4bKsw="}},{"startdate":"20240708","fullstartdate":"202407080700","enddate":"20240709","url":"/th?id=OHR.NorwayBlueberries_ROW6499030232_1920x1080.jpg&rf=LaDigue_1920x1080.jpg&pid=hp","urlbase":"/th?id=OHR.NorwayBlueberries_ROW6499030232","copyright":"Blueberries growing in the wild (© Baac3nes/Getty Images)","copyrightlink":"/search?q=Blueberry&form=hpcapt","title":"Info","quiz":"/search?q=Bing+homepage+quiz&filters=WQOskey:%22HPQuiz_20240708_NorwayBlueberries%22&FORM=HPQUIZ","wp":true,"hsh":"c4258ed68281039dda2506c18fd079b9","drk":1,"top":1,"bot":1,"hs":[],"og":{"img":"https://www.bing.com/th?id=OHR.NorwayBlueberries_ROW6499030232_tmb.jpg","title":"Info","desc":"Blueberries growing in the wild","hash":"MywGs1hLYU0voHeTuZna+Mvkqi0AWlucoVsAOTrokrY="}},{"startdate":"20240707","fullstartdate":"202407070700","enddate":"20240708","url":"/th?id=OHR.YenBaiTerraces_ROW6260255257_1920x1080.jpg&rf=LaDigue_1920x1080.jpg&pid=hp","urlbase":"/th?id=OHR.YenBaiTerraces_ROW6260255257","copyright":"Rice terraces of Mù Cang Chải, Yên Bái province, Vietnam (© Kiatanan Sugsompian/Getty Images)","copyrightlink":"/search?q=Rice+terraces+of+Mu+Cang+Chai&form=hpcapt","title":"Info","quiz":"/search?q=Bing+homepage+quiz&filters=WQOskey:%22HPQuiz_20240707_YenBaiTerraces%22&FORM=HPQUIZ","wp":true,"hsh":"6c611d209409cfc51bc9cc9fbd65e925","drk":1,"top":1,"bot":1,"hs":[],"og":{"img":"https://www.bing.com/th?id=OHR.YenBaiTerraces_ROW6260255257_tmb.jpg","title":"Info","desc":"Rice terraces of Mù Cang Chải, Yên Bái province, Vietnam","hash":"+WhOC3f/QRsZNc2utPW6c3R1UfQmApNiRYrVGg7orgg="}}],"tooltips":{"loading":"로드 중...","previous":"이전 이미지","next":"다음 이미지","walle":"이 이미지는 바탕화면으로 다운로드할 수 없습니다.","walls":"이미지를 다운로드하세요. 이 이미지는 바탕 화면에만 사용하도록 제한됩니다."}}