{"market":{"mkt":"pt-BR"},"images":[{"startdate":"20240217","fullstartdate":"202402170300","enddate":"20240218","url":"/th?id=OHR.LakeDolomites_PT-BR5853675668_1920x1080.jpg&rf=LaDigue_1920x1080.jpg&pid=hp","urlbase":"/th?id=OHR.LakeDolomites_PT-BR5853675668","copyright":"Lago Di Braies nas Dolomitas, Tirol do Sul, Itália (© Marco Bottigelli/Getty Images)","copyrightlink":"/search?q=lago+di+braies&form=hpcapt&mkt=pt-br","title":"Água de cor esmeralda","quiz":"/search?q=Bing+homepage+quiz&filters=WQOskey:%22HPQuiz_20240217_LakeDolomites%22&FORM=HPQUIZ","wp":true,"hsh":"d00549032bcb85d3aebf03170b4616d8","drk":1,"top":1,"bot":1,"hs":[],"og":{"img":"https://www.bing.com/th?id=OHR.LakeDolomites_PT-BR5853675668_tmb.jpg","title":"Água de cor esmeralda","desc":"Lago Di Braies nas Dolomitas, Tirol do Sul, Itália","hash":"5LwsCJIncm1hCz9ux4sa4u2QVQhCsPp4DKc65sPU1Tk="}},{"startdate":"20240216","fullstartdate":"202402160300","enddate":"20240217","url":"/th?id=OHR.BackyardBird_PT-BR4739609894_1920x1080.jpg&rf=LaDigue_1920x1080.jpg&pid=hp","urlbase":"/th?id=OHR.BackyardBird_PT-BR4739609894","copyright":"Female pyrrhuloxia perched on cactus plant, Texas (© outtakes/Getty Images)","copyrightlink":"/images/search?q=cardeis+aves&form=hpcapt&mkt=pt-br","title":"Viu algum pássaro hoje?","quiz":"/search?q=Bing+homepage+quiz&filters=WQOskey:%22HPQuiz_20240216_BackyardBird%22&FORM=HPQUIZ","wp":true,"hsh":"b1483dbcb73e2b91bac4c978c0f2c97c","drk":1,"top":1,"bot":1,"hs":[],"og":{"img":"https://www.bing.com/th?id=OHR.BackyardBird_PT-BR4739609894_tmb.jpg","title":"Viu algum pássaro hoje?","desc":"Cardeal-do-deserto, Texas, EUA","hash":"CUMWCTZlBG1WlUYQ4zR4PJJMeM/lDTHzU6OYZm5nfLk="}},{"startdate":"20240215","fullstartdate":"202402150300","enddate":"20240216","url":"/th?id=OHR.HippopotamusDay_PT-BR4524933452_1920x1080.jpg&rf=LaDigue_1920x1080.jpg&pid=hp","urlbase":"/th?id=OHR.HippopotamusDay_PT-BR4524933452","copyright":"Hippopotamus mother and calf, South Luangwa National Park, Zambia (© Nature Picture Library/Alamy)","copyrightlink":"/search?q=hipopotamo&form=hpcapt&mkt=pt-br","title":"Em terra ou na água","quiz":"/search?q=Bing+homepage+quiz&filters=WQOskey:%22HPQuiz_20240215_HippopotamusDay%22&FORM=HPQUIZ","wp":true,"hsh":"573b0b63b4e0ed0614c60bbe4560720a","drk":1,"top":1,"bot":1,"hs":[],"og":{"img":"https://www.bing.com/th?id=OHR.HippopotamusDay_PT-BR4524933452_tmb.jpg","title":"Em terra ou na água","desc":"Dia Mundial do Hipopótamo","hash":"9sh/s4QgBYRa2tUSUWfTq+Pnohy71E6p7UcsSrr7pio="}},{"startdate":"20240214","fullstartdate":"202402140300","enddate":"20240215","url":"/th?id=OHR.BowingCrane_PT-BR4236124881_1920x1080.jpg&rf=LaDigue_1920x1080.jpg&pid=hp","urlbase":"/th?id=OHR.BowingCrane_PT-BR4236124881","copyright":"Red-crowned crane bowing to his mate in Hokkaido, Japan (© Steve Bloom Images/Alamy)","copyrightlink":"/search?q=Historia+Dia+de+Sao+Valentin&form=hpcapt&mkt=pt-br","title":"Melhor juntos","quiz":"/search?q=Bing+homepage+quiz&filters=WQOskey:%22HPQuiz_20240214_BowingCrane%22&FORM=HPQUIZ","wp":true,"hsh":"ede58c6530bacfdc720a094fc81466f7","drk":1,"top":1,"bot":1,"hs":[],"og":{"img":"https://www.bing.com/th?id=OHR.BowingCrane_PT-BR4236124881_tmb.jpg","title":"Melhor juntos","desc":"Dia de São Valentim","hash":"0JauqwrmGTJbh4vtbAacjJ0Uon+Qk6lMjJ1D4126Q5k="}},{"startdate":"20240213","fullstartdate":"202402130300","enddate":"20240214","url":"/th?id=OHR.PegadungRocks_PT-BR4077101673_1920x1080.jpg&rf=LaDigue_1920x1080.jpg&pid=hp","urlbase":"/th?id=OHR.PegadungRocks_PT-BR4077101673","copyright":"Pegadung Rock, Lampung, Sumatra, Indonesia (© CK NG/500px/Getty Images)","copyrightlink":"/search?q=Lampung+Sumatra+Indonesia&form=hpcapt&mkt=pt-br","title":"Rochas “dentes de tubarão”","quiz":"/search?q=Bing+homepage+quiz&filters=WQOskey:%22HPQuiz_20240213_PegadungRocks%22&FORM=HPQUIZ","wp":true,"hsh":"86b9d2fe54347f66724e019e27d55e71","drk":1,"top":1,"bot":1,"hs":[],"og":{"img":"https://www.bing.com/th?id=OHR.PegadungRocks_PT-BR4077101673_tmb.jpg","title":"Rochas “dentes de tubarão”","desc":"Rocha de Pegadung, Lampung, Sumatra, Indonésia","hash":"IPqAj4qA7w9/DfwutgTJbpX0CxEXg1zcPQFR3XHvyYI="}},{"startdate":"20240212","fullstartdate":"202402120300","enddate":"20240213","url":"/th?id=OHR.GiantTortoise_PT-BR2643244597_1920x1080.jpg&rf=LaDigue_1920x1080.jpg&pid=hp","urlbase":"/th?id=OHR.GiantTortoise_PT-BR2643244597","copyright":"Volcán Alcedo giant tortoises, Isabela Island, Galápagos, Ecuador (© Tui De Roy/Minden Pictures)","copyrightlink":"/search?q=Ilha+Galapagos+Equador&form=hpcapt&mkt=pt-br","title":"Lar doce lar","quiz":"/search?q=Bing+homepage+quiz&filters=WQOskey:%22HPQuiz_20240212_GiantTortoise%22&FORM=HPQUIZ","wp":true,"hsh":"cb9895431a5c7d2148e1200234ae1868","drk":1,"top":1,"bot":1,"hs":[],"og":{"img":"https://www.bing.com/th?id=OHR.GiantTortoise_PT-BR2643244597_tmb.jpg","title":"Lar doce lar","desc":"Tartarugas gigantes de Galápagos, Equador","hash":"PpMv4ZsfRM3bF8NpL6IAOuLi6xoysOt20uVhLj4YZTc="}},{"startdate":"20240211","fullstartdate":"202402110300","enddate":"20240212","url":"/th?id=OHR.FolegandrosGreece_PT-BR2119893846_1920x1080.jpg&rf=LaDigue_1920x1080.jpg&pid=hp","urlbase":"/th?id=OHR.FolegandrosGreece_PT-BR2119893846","copyright":"Chora, Folegandros Island, Cyclades, Greece (© Francesco Riccardo Iacomino/Getty Images)","copyrightlink":"/search?q=Ilha+Folegandros+Grecia&form=hpcapt&mkt=pt-br","title":"Campos Elísios na Terra","quiz":"/search?q=Bing+homepage+quiz&filters=WQOskey:%22HPQuiz_20240211_FolegandrosGreece%22&FORM=HPQUIZ","wp":true,"hsh":"b71d3582855ef7730f31395edb22f36c","drk":1,"top":1,"bot":1,"hs":[],"og":{"img":"https://www.bing.com/th?id=OHR.FolegandrosGreece_PT-BR2119893846_tmb.jpg","title":"Campos Elísios na Terra","desc":"Ilha de Folegandros, Cíclades, Grécia","hash":"hcJgbEx46X05oVBofgin05wsqdSr+Et5ZNK77iQ7Hkw="}},{"startdate":"20240210","fullstartdate":"202402100300","enddate":"20240211","url":"/th?id=OHR.ChinaDragon_PT-BR1649344638_1920x1080.jpg&rf=LaDigue_1920x1080.jpg&pid=hp","urlbase":"/th?id=OHR.ChinaDragon_PT-BR1649344638","copyright":"Chinese New Year, Luzhou, China (© Liu Guoxing/VCG via Getty Images)","copyrightlink":"/search?q=Ano+Novo+Lunar+Curiosidades&form=hpcapt&mkt=pt-br","title":"O ano do Dragão","quiz":"/search?q=Bing+homepage+quiz&filters=WQOskey:%22HPQuiz_20240210_ChinaDragon%22&FORM=HPQUIZ","wp":false,"hsh":"4979bfc332f374970fa1e778b5f0f424","drk":1,"top":1,"bot":1,"hs":[],"og":{"img":"https://www.bing.com/th?id=OHR.ChinaDragon_PT-BR1649344638_tmb.jpg","title":"O ano do Dragão","desc":"Ano novo lunar, China","hash":"XzXb6+lEr7DH86CF1/jdVBU2PZJa+JhRtyIrRfcDTEs="}}],"tooltips":{"loading":"Carregando...","previous":"Imagem anterior","next":"Próxima imagem","walle":"Esta imagem não está disponível para ser baixada como papel de parede.","walls":"Baixe esta imagem. O uso desta imagem é restrito ao papel de parede."}}