{"market":{"mkt":"pt-BR"},"images":[{"startdate":"20240221","fullstartdate":"202402210300","enddate":"20240222","url":"/th?id=OHR.YosemiteFirefall_PT-BR5614973878_1920x1080.jpg&rf=LaDigue_1920x1080.jpg&pid=hp","urlbase":"/th?id=OHR.YosemiteFirefall_PT-BR5614973878","copyright":"Firefall at Horsetail Fall, Yosemite National Park, California (© Gregory B Cuvelier/Shutterstock)","copyrightlink":"/search?q=horsetail+firefall&form=hpcapt&mkt=pt-br","title":"Uma contradição natural","quiz":"/search?q=Bing+homepage+quiz&filters=WQOskey:%22HPQuiz_20240221_YosemiteFirefall%22&FORM=HPQUIZ","wp":true,"hsh":"d3e5f011c404b46e999654fdeb67aae8","drk":1,"top":1,"bot":1,"hs":[],"og":{"img":"https://www.bing.com/th?id=OHR.YosemiteFirefall_PT-BR5614973878_tmb.jpg","title":"Uma contradição natural","desc":"Cascata de fogo em Yosemite, EUA","hash":"VOLQj1hI+wBmeK419w/G9YLObA36fN8Sz9Zo5OJDziI="}},{"startdate":"20240220","fullstartdate":"202402200300","enddate":"20240221","url":"/th?id=OHR.PeakDistrictNP_PT-BR5424756118_1920x1080.jpg&rf=LaDigue_1920x1080.jpg&pid=hp","urlbase":"/th?id=OHR.PeakDistrictNP_PT-BR5424756118","copyright":"Kinder Scout at sunrise, Peak District National Park, England (© john finney photography/Getty Images)","copyrightlink":"/search?q=Kinder+Scout+Reino+Unido&form=hpcapt&mkt=pt-br","title":"Um destino para os aventureiros","quiz":"/search?q=Bing+homepage+quiz&filters=WQOskey:%22HPQuiz_20240220_PeakDistrictNP%22&FORM=HPQUIZ","wp":true,"hsh":"7a2ece6628693b169ae344057bbb29e7","drk":1,"top":1,"bot":1,"hs":[],"og":{"img":"https://www.bing.com/th?id=OHR.PeakDistrictNP_PT-BR5424756118_tmb.jpg","title":"Um destino para os aventureiros","desc":"Kinder Scout, Parque Nacional de Peak District, Reino Unido","hash":"7ydhALKxNP47bVU0++R9oFL3uubdL7zzEnJPHSaUdaI="}},{"startdate":"20240219","fullstartdate":"202402190300","enddate":"20240220","url":"/th?id=OHR.CarnavalTenerife_PT-BR5233903925_1920x1080.jpg&rf=LaDigue_1920x1080.jpg&pid=hp","urlbase":"/th?id=OHR.CarnavalTenerife_PT-BR5233903925","copyright":"Aerial view of colourful houses on a headland in Puerto de la Cruz, Tenerife, Spain (© Marco Bottigelli/Getty Images)","copyrightlink":"/search?q=Puerto+de+la+Cruz&form=hpcapt&mkt=pt-br","title":"Carnival Tenerife","quiz":"/search?q=Bing+homepage+quiz&filters=WQOskey:%22HPQuiz_20240219_CarnavalTenerife%22&FORM=HPQUIZ","wp":true,"hsh":"81ff2b6ebe12ab855f828f4d493cb909","drk":1,"top":1,"bot":1,"hs":[],"og":{"img":"https://www.bing.com/th?id=OHR.CarnavalTenerife_PT-BR5233903925_tmb.jpg","title":"Carnival Tenerife","desc":"Puerto de la Cruz, Tenerife, Espanha","hash":"QWVoTQNJ5XdXLtVU98inQ1IbW69RkdFwZ5EFViOKA+8="}},{"startdate":"20240218","fullstartdate":"202402180300","enddate":"20240219","url":"/th?id=OHR.DominicaWhales_PT-BR4985904903_1920x1080.jpg&rf=LaDigue_1920x1080.jpg&pid=hp","urlbase":"/th?id=OHR.DominicaWhales_PT-BR4985904903","copyright":"Sperm whale pod surfacing, Dominica (© Franco Banfi/Minden Pictures)","copyrightlink":"/search?q=cachalote&form=hpcapt&mkt=pt-br","title":"Tomando fôlego","quiz":"/search?q=Bing+homepage+quiz&filters=WQOskey:%22HPQuiz_20240218_DominicaWhales%22&FORM=HPQUIZ","wp":true,"hsh":"e588ce0b9543ee639ba35b0483912bef","drk":1,"top":1,"bot":1,"hs":[],"og":{"img":"https://www.bing.com/th?id=OHR.DominicaWhales_PT-BR4985904903_tmb.jpg","title":"Tomando fôlego","desc":"Dia Mundial da Baleia","hash":"wH2aJQuU3c5e3YI87jENDaG7PJuDGTfpJTORdh14cHk="}},{"startdate":"20240217","fullstartdate":"202402170300","enddate":"20240218","url":"/th?id=OHR.LakeDolomites_PT-BR5853675668_1920x1080.jpg&rf=LaDigue_1920x1080.jpg&pid=hp","urlbase":"/th?id=OHR.LakeDolomites_PT-BR5853675668","copyright":"Lago Di Braies nas Dolomitas, Tirol do Sul, Itália (© Marco Bottigelli/Getty Images)","copyrightlink":"/search?q=lago+di+braies&form=hpcapt&mkt=pt-br","title":"Água de cor esmeralda","quiz":"/search?q=Bing+homepage+quiz&filters=WQOskey:%22HPQuiz_20240217_LakeDolomites%22&FORM=HPQUIZ","wp":true,"hsh":"d00549032bcb85d3aebf03170b4616d8","drk":1,"top":1,"bot":1,"hs":[],"og":{"img":"https://www.bing.com/th?id=OHR.LakeDolomites_PT-BR5853675668_tmb.jpg","title":"Água de cor esmeralda","desc":"Lago Di Braies nas Dolomitas, Tirol do Sul, Itália","hash":"5LwsCJIncm1hCz9ux4sa4u2QVQhCsPp4DKc65sPU1Tk="}},{"startdate":"20240216","fullstartdate":"202402160300","enddate":"20240217","url":"/th?id=OHR.BackyardBird_PT-BR4739609894_1920x1080.jpg&rf=LaDigue_1920x1080.jpg&pid=hp","urlbase":"/th?id=OHR.BackyardBird_PT-BR4739609894","copyright":"Female pyrrhuloxia perched on cactus plant, Texas (© outtakes/Getty Images)","copyrightlink":"/images/search?q=cardeis+aves&form=hpcapt&mkt=pt-br","title":"Viu algum pássaro hoje?","quiz":"/search?q=Bing+homepage+quiz&filters=WQOskey:%22HPQuiz_20240216_BackyardBird%22&FORM=HPQUIZ","wp":true,"hsh":"b1483dbcb73e2b91bac4c978c0f2c97c","drk":1,"top":1,"bot":1,"hs":[],"og":{"img":"https://www.bing.com/th?id=OHR.BackyardBird_PT-BR4739609894_tmb.jpg","title":"Viu algum pássaro hoje?","desc":"Cardeal-do-deserto, Texas, EUA","hash":"CUMWCTZlBG1WlUYQ4zR4PJJMeM/lDTHzU6OYZm5nfLk="}},{"startdate":"20240215","fullstartdate":"202402150300","enddate":"20240216","url":"/th?id=OHR.HippopotamusDay_PT-BR4524933452_1920x1080.jpg&rf=LaDigue_1920x1080.jpg&pid=hp","urlbase":"/th?id=OHR.HippopotamusDay_PT-BR4524933452","copyright":"Hippopotamus mother and calf, South Luangwa National Park, Zambia (© Nature Picture Library/Alamy)","copyrightlink":"/search?q=hipopotamo&form=hpcapt&mkt=pt-br","title":"Em terra ou na água","quiz":"/search?q=Bing+homepage+quiz&filters=WQOskey:%22HPQuiz_20240215_HippopotamusDay%22&FORM=HPQUIZ","wp":true,"hsh":"573b0b63b4e0ed0614c60bbe4560720a","drk":1,"top":1,"bot":1,"hs":[],"og":{"img":"https://www.bing.com/th?id=OHR.HippopotamusDay_PT-BR4524933452_tmb.jpg","title":"Em terra ou na água","desc":"Dia Mundial do Hipopótamo","hash":"9sh/s4QgBYRa2tUSUWfTq+Pnohy71E6p7UcsSrr7pio="}},{"startdate":"20240214","fullstartdate":"202402140300","enddate":"20240215","url":"/th?id=OHR.BowingCrane_PT-BR4236124881_1920x1080.jpg&rf=LaDigue_1920x1080.jpg&pid=hp","urlbase":"/th?id=OHR.BowingCrane_PT-BR4236124881","copyright":"Red-crowned crane bowing to his mate in Hokkaido, Japan (© Steve Bloom Images/Alamy)","copyrightlink":"/search?q=Historia+Dia+de+Sao+Valentin&form=hpcapt&mkt=pt-br","title":"Melhor juntos","quiz":"/search?q=Bing+homepage+quiz&filters=WQOskey:%22HPQuiz_20240214_BowingCrane%22&FORM=HPQUIZ","wp":true,"hsh":"ede58c6530bacfdc720a094fc81466f7","drk":1,"top":1,"bot":1,"hs":[],"og":{"img":"https://www.bing.com/th?id=OHR.BowingCrane_PT-BR4236124881_tmb.jpg","title":"Melhor juntos","desc":"Dia de São Valentim","hash":"0JauqwrmGTJbh4vtbAacjJ0Uon+Qk6lMjJ1D4126Q5k="}}],"tooltips":{"loading":"Carregando...","previous":"Imagem anterior","next":"Próxima imagem","walle":"Esta imagem não está disponível para ser baixada como papel de parede.","walls":"Baixe esta imagem. O uso desta imagem é restrito ao papel de parede."}}